<?xml version="1.0" encoding="utf-8" ?>
<grammar>
  <production>
    <nonterminal>datafile</nonterminal>
    <expression>
      <sequence>
        <expression>
          <nonterminal>record</nonterminal>
        </expression>
        <expression>
          <terminal>.</terminal>
        </expression>
        <expression>
          <optional>
            <expression>
              <nonterminal>datafile</nonterminal>
            </expression>
          </optional>
        </expression>
      </sequence>
    </expression>
  </production>
  <production>
    <nonterminal>record</nonterminal>
    <expression>
      <sequence>
        <expression>
          <nonterminal>field</nonterminal>
        </expression>
        <expression>
          <optional>
            <expression>
              <sequence>
                <expression>
                  <terminal>;</terminal>
                </expression>
                <expression>
                  <nonterminal>record</nonterminal>
                </expression>
              </sequence>
            </expression>
          </optional>
        </expression>
      </sequence>
    </expression>
  </production>
  <production>
    <nonterminal>field</nonterminal>
    <expression>
      <choice>
        <expression>
          <nonterminal>integer_literal</nonterminal>
        </expression>
        <expression>
          <nonterminal>string_literal</nonterminal>
        </expression>
      </choice>
    </expression>
  </production>
</grammar>